aidenbots/__init__.py
aidenbots/bin/__init__.py
aidenbots/bin/classes.py
aidenbots/bin/utils.py
aidenbots/labware/eppendorf_96_well_lobind_plate_500ul.json
aidenbots/protocols/__init__.py
aidenbots/protocols/polar.py
aidenbots/protocols/zymo_magbead_extraction.py
aidenbots/sounds/begin.mp3
aidenbots-0.0.28.dev0.dist-info/LICENSE
aidenbots-0.0.28.dev0.dist-info/METADATA
aidenbots-0.0.28.dev0.dist-info/WHEEL
aidenbots-0.0.28.dev0.dist-info/entry_points.txt
aidenbots-0.0.28.dev0.dist-info/top_level.txt
aidenbots-0.0.28.dev0.dist-info/RECORD
