Metadata-Version: 2.1
Name: aidenbots
Version: 0.0.28.dev0
Summary: Opentrons automated protocols developed in the Aiden Lab
Home-page: https://github.com/aidenlab/ot2-bots
Author: Per Aspera Adastra
Author-email: adastra.aspera.per@gmail.com
License: MIT
Platform: UNKNOWN
Classifier: Programming Language :: Python :: 3
Classifier: License :: OSI Approved :: MIT License
Classifier: Operating System :: OS Independent
Requires-Python: >=3.7
Requires-Dist: opentrons (>=3.21.2)
